api/__init__.py
api/admin.py
api/api.py
api/apps.py
api/models.py
api/tests.py
api/views.py
api/migrations/0001_initial.py
api/migrations/0002_meeting_first_room.py
api/migrations/__init__.py
VideoWiki_room_BBB-8.0.dist-info/METADATA
VideoWiki_room_BBB-8.0.dist-info/WHEEL
VideoWiki_room_BBB-8.0.dist-info/top_level.txt
VideoWiki_room_BBB-8.0.dist-info/RECORD
