Metadata-Version: 2.1
Name: VideoWiki-room-BBB
Version: 8.0
Summary: VideoWiki Conferencing BigBlueButton
Home-page: UNKNOWN
Author: UNKNOWN
Author-email: UNKNOWN
License: UNKNOWN
Platform: UNKNOWN
Requires-Dist: Django (==3.2.5)
Requires-Dist: Pillow (==9.0.1)
Requires-Dist: PyJWT (==2.1.0)
Requires-Dist: Pygments (==2.14.0)
Requires-Dist: SecretStorage (==3.3.3)
Requires-Dist: asgiref (==3.4.1)
Requires-Dist: backports.zoneinfo (==0.2.1)
Requires-Dist: bleach (==6.0.0)
Requires-Dist: certifi (==2021.10.8)
Requires-Dist: cffi (==1.15.1)
Requires-Dist: charset-normalizer (==2.0.12)
Requires-Dist: cryptography (==40.0.1)
Requires-Dist: django-utils-six (==2.0)
Requires-Dist: djangorestframework-simplejwt (==4.7.2)
Requires-Dist: djangorestframework (==3.12.4)
Requires-Dist: docutils (==0.19)
Requires-Dist: idna (==3.3)
Requires-Dist: importlib-metadata (==6.1.0)
Requires-Dist: importlib-resources (==5.12.0)
Requires-Dist: jaraco.classes (==3.2.3)
Requires-Dist: jeepney (==0.8.0)
Requires-Dist: keyring (==23.13.1)
Requires-Dist: markdown-it-py (==2.2.0)
Requires-Dist: mdurl (==0.1.2)
Requires-Dist: more-itertools (==9.1.0)
Requires-Dist: nose (==1.3.7)
Requires-Dist: pkginfo (==1.9.6)
Requires-Dist: pycparser (==2.21)
Requires-Dist: python-dotenv (==1.0.0)
Requires-Dist: pytz (==2021.1)
Requires-Dist: readme-renderer (==37.3)
Requires-Dist: requests-toolbelt (==0.10.1)
Requires-Dist: requests (==2.27.1)
Requires-Dist: rfc3986 (==2.0.0)
Requires-Dist: rich (==13.3.3)
Requires-Dist: six (==1.16.0)
Requires-Dist: sqlparse (==0.4.1)
Requires-Dist: twine (==4.0.2)
Requires-Dist: typing-extensions (==4.5.0)
Requires-Dist: urllib3 (==1.26.9)
Requires-Dist: webencodings (==0.5.1)
Requires-Dist: zipp (==3.15.0)
